LICENSE
MANIFEST.in
README.rst
setup.py
cmsplugin_feedback/__init__.py
cmsplugin_feedback/admin.py
cmsplugin_feedback/cms_plugins.py
cmsplugin_feedback/forms.py
cmsplugin_feedback/models.py
cmsplugin_feedback/settings.py
cmsplugin_feedback/signals.py
cmsplugin_feedback/urls.py
cmsplugin_feedback/views.py
cmsplugin_feedback.egg-info/PKG-INFO
cmsplugin_feedback.egg-info/SOURCES.txt
cmsplugin_feedback.egg-info/dependency_links.txt
cmsplugin_feedback.egg-info/not-zip-safe
cmsplugin_feedback.egg-info/requires.txt
cmsplugin_feedback.egg-info/top_level.txt
cmsplugin_feedback/locale/ar/LC_MESSAGES/django.mo
cmsplugin_feedback/locale/ar/LC_MESSAGES/django.po
cmsplugin_feedback/locale/be/LC_MESSAGES/django.mo
cmsplugin_feedback/locale/be/LC_MESSAGES/django.po
cmsplugin_feedback/locale/en/LC_MESSAGES/django.mo
cmsplugin_feedback/locale/en/LC_MESSAGES/django.po
cmsplugin_feedback/locale/ru/LC_MESSAGES/django.mo
cmsplugin_feedback/locale/ru/LC_MESSAGES/django.po
cmsplugin_feedback/migrations/0001_initial.py
cmsplugin_feedback/migrations/__init__.py
cmsplugin_feedback/south_migrations/0001_initial.py
cmsplugin_feedback/south_migrations/0002_auto__del_field_feedbackplugin_title.py
cmsplugin_feedback/south_migrations/0003_auto__del_field_feedbackplugin_submit.py
cmsplugin_feedback/south_migrations/0004_auto__del_field_feedbackplugin_ok_message.py
cmsplugin_feedback/south_migrations/__init__.py
cmsplugin_feedback/templates/cms/plugins/feedback-email.html
cmsplugin_feedback/templates/cms/plugins/feedback.html
cmsplugin_feedback/templatetags/__init__.py
cmsplugin_feedback/templatetags/feedback_tags.py