Metadata-Version: 1.1
Name: cmsplugin-feedback
Version: 0.3.1
Summary: Feedback form plugin for Django CMS
Home-page: https://github.com/satyrius/cmsplugin-feedback
Author: Anton Egorov
Author-email: anton.egoroff@gmail.com
License: MIT
Platform: OS Independent
Classifier: Development Status :: 5 - Production/Stable
Classifier: Environment :: Web Environment
Classifier: Framework :: Django
Classifier: Intended Audience :: Developers
Classifier: License :: OSI Approved :: MIT License
Classifier: Operating System :: OS Independent
Classifier: Programming Language :: Python
Classifier: Topic :: Communications
Classifier: Topic :: Internet :: WWW/HTTP :: Dynamic Content
Classifier: Programming Language :: Python :: 2.7
